jacob_os_version_check-0.4.2.dist-info/METADATA
jacob_os_version_check-0.4.2.dist-info/WHEEL
jacob_os_version_check-0.4.2.dist-info/entry_points.txt
jacob_os_version_check/__init__.py
jacob_os_version_check/hi.py
jacob_os_version_check/osver.py
jacob_os_version_check-0.4.2.dist-info/RECORD
