Metadata-Version: 2.1
Name: jacob-os-version-check
Version: 0.4.2
Summary: Detects and outputs the os vesion.
Author-Email: jacob53 <jacob8753@gmail.com>
License: MIT
Project-URL: Homepage, https://github.com/Jacob-53/jacob-os-version-check
Project-URL: Issues, https://github.com/Jacob-53/jacob-os-version-check/issues
Requires-Python: >=3.10
Requires-Dist: check-os-ver>=0.2.1
Requires-Dist: hj-check-os-version>=0.2.1
Requires-Dist: lucas-check-os-ver>=0.2.1
Requires-Dist: stundrg-check-os-ver>=0.2.3
Requires-Dist: cho-check-os-ver>=0.2.3
Requires-Dist: nunininu-check-os-ver>=0.3.0
Requires-Dist: seo-check-os-version>=0.2.0
